hrequests/__init__.py
hrequests/__main__.py
hrequests/__version__.py
hrequests/bin/LICENSE.txt
hrequests/bin/__init__.py
hrequests/browser/__init__.py
hrequests/browser/browser.py
hrequests/browser/chrome.py
hrequests/browser/common.py
hrequests/browser/engine.py
hrequests/browser/firefox.py
hrequests/browser/proxy.py
hrequests/cffi.py
hrequests/client.py
hrequests/cookies.py
hrequests/exceptions.py
hrequests/parser.py
hrequests/proxies/__init__.py
hrequests/proxies/evomi.py
hrequests/proxies/mixin.py
hrequests/reqs.py
hrequests/response.py
hrequests/session.py
hrequests/toolbelt.py
hrequests-0.9.2.dist-info/LICENSE
hrequests-0.9.2.dist-info/METADATA
hrequests-0.9.2.dist-info/WHEEL
hrequests-0.9.2.dist-info/RECORD
