Metadata-Version: 2.1
Name: hrequests
Version: 0.9.2
Summary: Hrequests (human requests) is a simple, configurable, feature-rich, replacement for the Python requests library.
Home-page: https://github.com/daijro/hrequests
License: Apache-2.0
Keywords: tls,client,http,scraping,requests,humans,playwright
Author: daijro
Author-email: daijro.dev@gmail.com
Requires-Python: >=3.8,<4.0
Classifier: License :: OSI Approved :: Apache Software License
Classifier: Programming Language :: Python :: 3
Classifier: Programming Language :: Python :: 3.8
Classifier: Programming Language :: Python :: 3.9
Classifier: Programming Language :: Python :: 3.10
Classifier: Programming Language :: Python :: 3.11
Classifier: Programming Language :: Python :: 3.12
Classifier: Programming Language :: Python :: 3.13
Classifier: Topic :: Internet :: WWW/HTTP
Classifier: Topic :: Internet :: WWW/HTTP :: Browsers
Classifier: Topic :: Software Development :: Libraries :: Python Modules
Provides-Extra: all
Provides-Extra: chrome
Provides-Extra: firefox
Requires-Dist: aioprocessing
Requires-Dist: async-class
Requires-Dist: browserforge (==1.1.2)
Requires-Dist: camoufox[geoip] (>=0.3.9,<0.4.0) ; extra == "all" or extra == "firefox"
Requires-Dist: faust-cchardet
Requires-Dist: geventhttpclient
Requires-Dist: httpx
Requires-Dist: msvc-runtime ; sys_platform == "win32" and python_version < "3.13"
Requires-Dist: numpy
Requires-Dist: orjson
Requires-Dist: parse
Requires-Dist: patchright ; extra == "all" or extra == "chrome"
Requires-Dist: playwright ; extra == "all" or extra == "firefox"
Requires-Dist: rich
Requires-Dist: rich-click
Requires-Dist: selectolax
Requires-Dist: typing-extensions
Requires-Dist: ua_parser
Requires-Dist: urllib3
Requires-Dist: zstandard
Project-URL: Documentation, https://daijro.gitbook.io/hrequests/
Project-URL: Repository, https://github.com/daijro/hrequests
